tarksr/__init__.py
tarksr/ak.py
tarksr/cgi.py
tarksr/exception.py
tarksr-0.0.2.dist-info/LICENSE
tarksr-0.0.2.dist-info/METADATA
tarksr-0.0.2.dist-info/WHEEL
tarksr-0.0.2.dist-info/top_level.txt
tarksr-0.0.2.dist-info/RECORD
