Metadata-Version: 2.1
Name: tarksr
Version: 0.0.2
Summary: 二改的明日方舟国服请求库
Home-page: https://github.com/TNXG/py_arknights
Author: TNXG
Author-email: mcminecraftmc@126.com
License: UNKNOWN
Platform: UNKNOWN
Classifier: Programming Language :: Python :: 3
Requires-Python: >=3.6
License-File: LICENSE
